petekutils/__init__.py
petekutils/json_util.py
petekutils/serializer.py
petekutils/text_util.py
petekutils-1.1.3.dist-info/DESCRIPTION.rst
petekutils-1.1.3.dist-info/METADATA
petekutils-1.1.3.dist-info/RECORD
petekutils-1.1.3.dist-info/WHEEL
petekutils-1.1.3.dist-info/metadata.json
petekutils-1.1.3.dist-info/top_level.txt
