Metadata-Version: 2.0
Name: petekutils
Version: 1.1.3
Summary: Peteksoft Utils
Home-page: UNKNOWN
Author: Bahattin Zorlu
Author-email: bahattin.zorlu@hotmail.com
License: UNKNOWN
Platform: UNKNOWN
Requires-Dist: requests (==2.13.0)
Requires-Dist: django (==1.11)
